<Ui xmlns="http://www.blizzard.com/wow/ui/">	
	<Script file="developer\reloadui.lua"/>
	<Script file="developer\commands.lua"/>
	<Script file="core\init.lua"/>
	<Script file="core\constants.lua"/>	
	<Script file="locales\english.lua"/>
	<Script file="locales\french.lua"/>
	<Script file="locales\russian.lua"/>
	<Script file="locales\german.lua"/>
	<Script file="locales\taiwan.lua"/>
	<Script file="locales\spanish.lua"/>
	<Script file="locales\korean.lua"/>	
	<Script file="config\config.lua"/>
	<Script file="config\profiles.lua"/>
	<Script file="medias\medias.lua"/>	
	<Script file="core\configui.lua"/>
	<Include file="modules\unitframes\core\oUF\oUF.xml"/>
	<Script file="modules\unitframes\plugins\oUF_AuraWatch\oUF_AuraWatch.lua"/>
	<Script file="modules\unitframes\plugins\oUF_CombatFeedback\oUF_CombatFeedback.lua"/>
	<Script file="modules\unitframes\plugins\oUF_DebuffHighlight\oUF_DebuffHighlight.lua"/>
	<Script file="modules\unitframes\plugins\oUF_Experience\oUF_Experience.lua"/>
	<Script file="modules\unitframes\plugins\oUF_MovableFrames\movable.lua"/>
	<Script file="modules\unitframes\plugins\oUF_Reputation\oUF_Reputation.lua"/>
	<Script file="modules\unitframes\plugins\oUF_Smooth\oUF_Smooth.lua"/>
	<Script file="modules\unitframes\plugins\oUF_TotemBar\oUF_TotemBar.lua"/>
	<Script file="modules\unitframes\plugins\oUF_Trinkets\oUF_Trinkets.lua"/>
	<Script file="modules\unitframes\plugins\oUF_RaidDebuffs\oUF_RaidDebuffs.lua"/>	
	<Script file="modules\unitframes\plugins\oUF_WeakenedSoul\oUF_WeakenedSoul.lua"/>	
	<Script file="modules\unitframes\templates\colors.lua"/>
	<Script file="core\uiscale.lua"/>
	<Script file="core\deprecated.lua"/>
	<Script file="core\api.lua"/>
	<Script file="core\functions.lua"/>
	<Script file="core\launch.lua"/>
	<Script file="core\disable.lua"/>
	<Script file="core\clientfonts.lua"/>
	<Script file="modules\blizzard\watchframe.lua"/>
	<Script file="modules\blizzard\durability.lua"/>
	<Script file="modules\blizzard\vehicle.lua"/>
	<Script file="modules\blizzard\capturebar.lua"/>
	<Script file="modules\blizzard\gm.lua"/>
	<Script file="modules\blizzard\ghostframe.lua"/>
	<Script file="modules\misc\commands.lua"/>
	<Script file="modules\blizzard\quests.lua"/>
	<Script file="modules\misc\invite.lua"/>
	<Script file="modules\misc\damage.lua"/>
	<Script file="modules\loot\autodez.lua"/>
	<Script file="modules\blizzard\symbol.lua"/>
	<Script file="modules\loot\merchant.lua"/>
	<Script file="modules\blizzard\error.lua"/>
	<Script file="modules\chat\copyurl.lua"/>
	<Script file="modules\tooltip\itemidcount.lua"/>
	<Script file="modules\blizzard\kill.lua"/>
	<Script file="modules\chat\spam.lua"/>	
	<Script file="modules\blizzard\font.lua"/>
	<Include file="modules\buffs\template.xml"/>
	<Script file="modules\buffs\buffs.lua"/>
	<Script file="modules\maps\minimap.lua"/>
	<Script file="modules\panels\panels.lua"/>
	<Script file="modules\datatext\armor.lua"/>
	<Script file="modules\datatext\avoidance.lua"/>
	<Script file="modules\datatext\bags.lua"/>
	<Script file="modules\datatext\battleground.lua"/>
	<Script file="modules\datatext\crit.lua"/>
	<Script file="modules\datatext\dps.lua"/>
	<Script file="modules\datatext\durability.lua"/>
	<Script file="modules\datatext\fps.lua"/>
	<Script file="modules\datatext\friend.lua"/>
	<Script file="modules\datatext\gold.lua"/>
	<Script file="modules\datatext\guild.lua"/>
	<Script file="modules\datatext\haste.lua"/>
	<Script file="modules\datatext\hps.lua"/>
	<Script file="modules\datatext\system.lua"/>
	<Script file="modules\datatext\power.lua"/>
	<Script file="modules\datatext\time.lua"/>
	<Script file="modules\datatext\currency.lua"/>
	<Script file="modules\datatext\hit.lua"/>
	<Script file="modules\datatext\micromenu.lua"/>
	<Script file="modules\datatext\mastery.lua"/>
	<Script file="modules\actionbars\Bind.lua"/>
	<Script file="modules\actionbars\Hide.lua"/>
	<Script file="modules\actionbars\Bar1.lua"/>
	<Script file="modules\actionbars\Bar2.lua"/>
	<Script file="modules\actionbars\Bar3.lua"/>
	<Script file="modules\actionbars\Bar4.lua"/>
	<Script file="modules\actionbars\Bar5.lua"/>
	<Script file="modules\actionbars\Bar6.lua"/>
	<Script file="modules\actionbars\Bar7.lua"/>
	<Script file="modules\actionbars\BarPet.lua"/>
	<Script file="modules\actionbars\BarShift.lua"/>
	<Script file="modules\actionbars\BarTotem.lua"/>
	<Script file="modules\actionbars\buttons.lua"/>	
	<Script file="modules\actionbars\Style.lua"/>
	<Script file="modules\actionbars\Range.lua"/>
	<Script file="modules\actionbars\Others.lua"/>
	<Script file="modules\actionbars\Cooldowns.lua"/>	
	<Script file="modules\chat\chatframes.lua"/>
	<Script file="modules\chat\telltarget.lua"/>
	<Script file="modules\chat\copychat.lua"/>
	<Script file="modules\chat\mousescroll.lua"/>
	<Script file="modules\chat\sounds.lua"/>
	<Script file="modules\tooltip\tooltip.lua"/>
	<Script file="modules\nameplates\nameplates.lua"/>
	<Script file="modules\bags\bags.lua"/>
	<Script file="modules\loot\lootframe.lua"/>
	<Script file="modules\loot\rollframe.lua"/>
	<Script file="modules\maps\worldmap.lua"/>
	<Script file="modules\maps\zonemap.lua"/>
	<Script file="modules\blizzard\mirror.lua"/>
	<Script file="modules\notifications\selfbuffs.lua"/>
	<Script file="modules\skins\blizzardframes.lua"/>
	<Script file="modules\skins\bubbles.lua"/>	
	<Include file="modules\unitframes\templates\tankassist.xml"/>
	<Script file="modules\unitframes\tags\tags.lua"/>
	<Script file="modules\unitframes\layouts\tukui.lua"/>
	<Script file="modules\notifications\hunterpethappiness.lua"/>	
	<Script file="modules\misc\altpowerbar.lua"/>
	<Script file="modules\misc\threatbar.lua"/>
	<Script file="modules\blizzard\achievements.lua"/>
	<Script file="core\movers.lua"/>
	<Script file="developer\test.lua"/>
</Ui>